{"cameraMode":{"drawMode":0,"name":"Shaded","section":"Shading Mode"},"sceneLighting":true,"audioPlay":false,"sceneViewState":{"m_AlwaysRefresh":false,"showFog":true,"showSkybox":false,"showFlares":true,"showImageEffects":true,"showParticleSystems":true,"showVisualEffectGraphs":true,"m_FxEnabled":true},"in2DMode":false,"pivot":{"x":-2.445409059524536,"y":1.0503718852996827,"z":-0.5285457372665405},"rotation":{"x":-0.11822566390037537,"y":0.6631515026092529,"z":-0.1071789562702179,"w":-0.7313334941864014},"size":1.3332840204238892,"orthographic":false}